{
    "name": "Stage 2, Level 13 - Buren's Columns",
	"img": "bomberman-assets/imgs/levels/level-12.png",
    "height": 11,
    "width": 19,
	"time": 150,
	"wallGenPercent": 40,
    "objects": {
		"outside": ".",
        "empty": " ",
        "player": "p",
        "wall": "w",
        "block": "b",
        "crispy": "c",
        "flag": "f",
        "end": "e",
		"safe": "_",
        "enemyBasic": "0",
        "enemyWithEye": "1",
        "enemyFollow": "2",
        "enemyFly": "3",
        "enemyCrispy": "4",
        "enemyFrog": "5"
    },
    "map": [
        { "0": "wwwwwwwwwwwwwwwwwww", "1": "wwwwwwwwwwwwwwwwwww" },
        { "0": "wp_c       ____0_ w", "1": "w                 w" },
        { "0": "w_b b b b b b b b w", "1": "w                 w" },
        { "0": "wc                w", "1": "w                 w" },
        { "0": "w b b b b b b b b w", "1": "w                 w" },
        { "0": "w          4      w", "1": "w                 w" },
        { "0": "w b b b b b b b b w", "1": "w                 w" },
        { "0": "w    1            w", "1": "w                 w" },
        { "0": "w b b b b b b b b w", "1": "w                 w" },
        { "0": "w       5c   5 3  w", "1": "w                 w" },
        { "0": "wwwwwwwwwewwwwwwwww", "1": "wwwwwwwwwwwwwwwwwww" }
    ],
    "bonus": {
        "bombs": {
            "chance": 15,
            "nb": -1
        },
        "flames": {
            "chance": 10,
            "nb": -1
        },
        "speed": {
            "chance": 10,
            "nb": 2
        },
        "shield": {
            "chance": 5,
            "nb": 1
        },
        "time": {
            "chance": 20,
            "nb": 1
        },
        "points": {
            "chance": 15,
            "nb": 3
        }
    }
}
